AssignHotSpareREDFISH.py
BiosChangePasswordREDFISH.py
BiosDeviceRecoveryREDFISH.py
BiosResetToDefaultsREDFISH.py
BlinkUnBlinkTargetREDFISH.py
BootToNetworkIsoOsdREDFISH.py
CHANGELOG.txt
CancelCheckConsistencyVirtualDiskREDFISH.py
ChangeBiosBootOrderREDFISH.py
ChangeIdracUserPasswordREDFISH.py
ChangePdStateREDFISH.py
ChangeVirtualDiskAttributesREDFISH.py
CheckConsistencyVirtualDiskREDFISH.py
ClearForeignConfigREDFISH.py
ConvertToNonRAIDREDFISH.py
ConvertToRAIDREDFISH.py
CreateDeleteIdracUsersREDFISH.py
CreateServerRebootJobREDFISH.py
CreateVirtualDiskREDFISH.py
CreateXAuthTokenSessionREDFISH.py
DeleteFirmwarePackageREDFISH.py
DeleteJobQueueREDFISH.py
DeleteVirtualDiskREDFISH.py
DellSwitchConnectionCollectionREDFISH.py
DeviceFirmwareMultipartUploadREDFISH.py
DeviceFirmwareRollbackMultipleDevicesREDFISH.py
DeviceFirmwareRollbackREDFISH.py
DeviceFirmwareSimpleUpdateCheckVersionREDFISH.py
DeviceFirmwareSimpleUpdateREDFISH.py
DeviceFirmwareSimpleUpdateTransferProtocolREDFISH.py
EnableDisableBiosBootOrderDevicesREDFISH.py
ExportClearSerialDataLogsREDFISH.py
ExportFactoryConfigurationREDFISH.py
ExportHWInventoryREDFISH.py
ExportImportSSLCertificateREDFISH.py
ExportLCLogREDFISH.py
ExportServerScreenShotREDFISH.py
ExportSystemConfigurationLocalREDFISH.py
ExportSystemConfigurationNetworkShareREDFISH.py
ExportThermalHistoryREDFISH.py
ExportVideoLogREDFISH.py
FirmwareUpdateLocalRepoREDFISH.py
GenerateCsrREDFISH.py
GetAssemblyInventoryREDFISH.py
GetDHSDisksREDFISH.py
GetDeleteiDRACSessionsREDFISH.py
GetDiskOperationREDFISH.py
GetEthernetInterfacesREDFISH.py
GetFirmwareInventoryREDFISH.py
GetIdracLcLogsREDFISH.py
GetIdracLcSystemAttributesREDFISH.py
GetIdracMessageRegistryREDFISH.py
GetIdracSelLogsREDFISH.py
GetIdracServerSlotInformationREDFISH.py
GetIdracServiceRootDetailsNoCredsREDFISH.py
GetNvDimmInventoryREDFISH.py
GetOSInformationREDFISH.py
GetOSNetworkInformationREDFISH.py
GetPCIeDeviceInventoryREDFISH.py
GetRAIDLevelsREDFISH.py
GetRemoteServicesAPIStatusREDFISH.py
IdracRedfishSupport.egg-info/SOURCES.txt
IdracRedfishSupport.egg-info/dependency_links.txt
IdracRedfishSupport.egg-info/requires.txt
IdracRedfishSupport.egg-info/top_level.txt
IdracRedfishSupportTest.egg-info/PKG-INFO
IdracRedfishSupportTest.egg-info/SOURCES.txt
IdracRedfishSupportTest.egg-info/dependency_links.txt
IdracRedfishSupportTest.egg-info/requires.txt
IdracRedfishSupportTest.egg-info/top_level.txt