Metadata-Version: 2.1
Name: IdracRedfishSupportTest
Version: 0.0.7
Summary: iDRAC Redfish API support for multiple iDRAC workflows.
Home-page: https://github.com/dell/iDRAC-Redfish-Scripting
Author: Texas Roemer
Author-email: texas_roemer@dell.com
License: GPLv2
Keywords: python,Redfish,IDRAC
Platform: UNKNOWN
License-File: LICENSE.txt
